LICENSE
MANIFEST.in
README.md
setup.cfg
setup.py
docassemble/__init__.py
docassemble.LAWVLegalHelpforRenters.egg-info/PKG-INFO
docassemble.LAWVLegalHelpforRenters.egg-info/SOURCES.txt
docassemble.LAWVLegalHelpforRenters.egg-info/dependency_links.txt
docassemble.LAWVLegalHelpforRenters.egg-info/namespace_packages.txt
docassemble.LAWVLegalHelpforRenters.egg-info/not-zip-safe
docassemble.LAWVLegalHelpforRenters.egg-info/requires.txt
docassemble.LAWVLegalHelpforRenters.egg-info/top_level.txt
docassemble/LAWVLegalHelpforRenters/__init__.py
docassemble/LAWVLegalHelpforRenters/data/questions/informal_hearing_request.yml
docassemble/LAWVLegalHelpforRenters/data/questions/petition_for_appeal.yml
docassemble/LAWVLegalHelpforRenters/data/questions/return_of_security_deposit.yml
docassemble/LAWVLegalHelpforRenters/data/questions/return_personal_property.yml
docassemble/LAWVLegalHelpforRenters/data/questions/warranty_of_habitability.yml
docassemble/LAWVLegalHelpforRenters/data/questions/wrongful_occ_answer.yml
docassemble/LAWVLegalHelpforRenters/data/sources/README.md
docassemble/LAWVLegalHelpforRenters/data/static/README.md
docassemble/LAWVLegalHelpforRenters/data/static/bill.png
docassemble/LAWVLegalHelpforRenters/data/static/civil_judgment_order_rental.png
docassemble/LAWVLegalHelpforRenters/data/static/code.png
docassemble/LAWVLegalHelpforRenters/data/static/compilation.jpg
docassemble/LAWVLegalHelpforRenters/data/static/cotenant.png
docassemble/LAWVLegalHelpforRenters/data/static/factory_home.jpg
docassemble/LAWVLegalHelpforRenters/data/static/hammer.png
docassemble/LAWVLegalHelpforRenters/data/static/house.png
docassemble/LAWVLegalHelpforRenters/data/static/mailbox.png
docassemble/LAWVLegalHelpforRenters/data/static/order_of_possession.png
docassemble/LAWVLegalHelpforRenters/data/static/people.png
docassemble/LAWVLegalHelpforRenters/data/static/people_inside.png
docassemble/LAWVLegalHelpforRenters/data/static/room.png
docassemble/LAWVLegalHelpforRenters/data/static/wrongful_occupation_petition.png
docassemble/LAWVLegalHelpforRenters/data/static/wrongful_occupation_summons.png
docassemble/LAWVLegalHelpforRenters/data/templates/README.md
docassemble/LAWVLegalHelpforRenters/data/templates/informal_hearing_eviction.docx
docassemble/LAWVLegalHelpforRenters/data/templates/informal_hearing_termination.docx
